[
    {
        "temperature": 18.37,
        "humidity": 60.83,
        "brightness": 0.51,
        "timestamp": "2026-01-14T03:36:28.466668"
    },
    {
        "temperature": 18.59,
        "humidity": 62.04,
        "brightness": 0.89,
        "timestamp": "2026-01-14T03:36:08.413877"
    },
    {
        "temperature": 19.74,
        "humidity": 65.69,
        "brightness": 0.81,
        "timestamp": "2026-01-14T03:35:48.361032"
    },
    {
        "temperature": 18.75,
        "humidity": 57.26,
        "brightness": 0.8,
        "timestamp": "2026-01-14T03:35:28.301870"
    },
    {
        "temperature": 20.56,
        "humidity": 64.76,
        "brightness": 0.45,
        "timestamp": "2026-01-14T03:35:19.773621"
    },
    {
        "temperature": 21.59,
        "humidity": 64.76,
        "brightness": 0.87,
        "timestamp": "2026-01-14T03:34:59.719813"
    },
    {
        "temperature": 20.36,
        "humidity": 65.94,
        "brightness": 0.71,
        "timestamp": "2026-01-14T03:34:39.660935"
    },
    {
        "temperature": 20.14,
        "humidity": 64.95,
        "brightness": 0.71,
        "timestamp": "2026-01-14T03:34:19.601400"
    },
    {
        "temperature": 20.02,
        "humidity": 53.94,
        "brightness": 0.39,
        "timestamp": "2026-01-14T03:33:59.547162"
    },
    {
        "temperature": 20.58,
        "humidity": 55.11,
        "brightness": 0.99,
        "timestamp": "2026-01-14T03:33:39.496245"
    },
    {
        "temperature": 18.14,
        "humidity": 52.42,
        "brightness": 0.71,
        "timestamp": "2026-01-14T03:33:19.446721"
    },
    {
        "temperature": 21.05,
        "humidity": 68.93,
        "brightness": 0.55,
        "timestamp": "2026-01-14T03:32:59.390664"
    },
    {
        "temperature": 20.6,
        "humidity": 67.04,
        "brightness": 0.46,
        "timestamp": "2026-01-14T03:32:39.336772"
    },
    {
        "temperature": 18.95,
        "humidity": 66.51,
        "brightness": 0.7,
        "timestamp": "2026-01-14T03:32:19.283050"
    },
    {
        "temperature": 21.27,
        "humidity": 62.87,
        "brightness": 0.94,
        "timestamp": "2026-01-14T03:31:59.229029"
    },
    {
        "temperature": 21.31,
        "humidity": 60.66,
        "brightness": 0.8,
        "timestamp": "2026-01-14T03:31:43.414670"
    },
    {
        "temperature": 21.08,
        "humidity": 68.35,
        "brightness": 0.59,
        "timestamp": "2026-01-14T03:31:23.364791"
    },
    {
        "temperature": 20.15,
        "humidity": 64.55,
        "brightness": 0.45,
        "timestamp": "2026-01-14T03:31:03.306933"
    },
    {
        "temperature": 18.38,
        "humidity": 66.47,
        "brightness": 0.41,
        "timestamp": "2026-01-14T03:30:43.261626"
    },
    {
        "temperature": 20.86,
        "humidity": 50.68,
        "brightness": 0.58,
        "timestamp": "2026-01-14T03:30:23.216338"
    },
    {
        "temperature": 20.52,
        "humidity": 61.96,
        "brightness": 0.42,
        "timestamp": "2026-01-14T03:30:03.158248"
    },
    {
        "temperature": 20.9,
        "humidity": 59.08,
        "brightness": 0.64,
        "timestamp": "2026-01-14T03:29:43.100095"
    },
    {
        "temperature": 20.55,
        "humidity": 53.65,
        "brightness": 0.63,
        "timestamp": "2026-01-14T03:29:23.049484"
    },
    {
        "temperature": 19.05,
        "humidity": 51.45,
        "brightness": 0.34,
        "timestamp": "2026-01-14T03:29:03.006583"
    },
    {
        "temperature": 18.4,
        "humidity": 59.51,
        "brightness": 0.87,
        "timestamp": "2026-01-14T03:28:42.953914"
    },
    {
        "temperature": 19.33,
        "humidity": 62.34,
        "brightness": 0.92,
        "timestamp": "2026-01-14T03:28:22.908933"
    },
    {
        "temperature": 18.86,
        "humidity": 59.43,
        "brightness": 0.69,
        "timestamp": "2026-01-14T03:28:02.859929"
    },
    {
        "temperature": 20.49,
        "humidity": 55.78,
        "brightness": 0.88,
        "timestamp": "2026-01-14T03:27:42.805752"
    },
    {
        "temperature": 19.22,
        "humidity": 62.8,
        "brightness": 0.84,
        "timestamp": "2026-01-14T03:27:22.751122"
    },
    {
        "temperature": 18.5,
        "humidity": 52.5,
        "brightness": 0.31,
        "timestamp": "2026-01-14T03:27:02.700920"
    },
    {
        "temperature": 19.68,
        "humidity": 65.51,
        "brightness": 0.65,
        "timestamp": "2026-01-14T03:26:42.644798"
    },
    {
        "temperature": 18.38,
        "humidity": 68.88,
        "brightness": 0.94,
        "timestamp": "2026-01-14T03:26:26.999951"
    },
    {
        "temperature": 20.06,
        "humidity": 54.11,
        "brightness": 0.38,
        "timestamp": "2026-01-14T03:26:06.947243"
    },
    {
        "temperature": 20.93,
        "humidity": 65.61,
        "brightness": 0.85,
        "timestamp": "2026-01-14T03:25:46.900585"
    },
    {
        "temperature": 20.27,
        "humidity": 62.02,
        "brightness": 0.59,
        "timestamp": "2026-01-14T03:25:26.842804"
    },
    {
        "temperature": 19.67,
        "humidity": 67.4,
        "brightness": 0.39,
        "timestamp": "2026-01-14T03:25:06.794356"
    },
    {
        "temperature": 19.51,
        "humidity": 57.25,
        "brightness": 0.36,
        "timestamp": "2026-01-14T03:24:46.740603"
    },
    {
        "temperature": 18.41,
        "humidity": 55.1,
        "brightness": 0.99,
        "timestamp": "2026-01-14T03:24:26.683031"
    },
    {
        "temperature": 18.8,
        "humidity": 55.0,
        "brightness": 0.62,
        "timestamp": "2026-01-14T03:24:06.626503"
    },
    {
        "temperature": 21.44,
        "humidity": 66.99,
        "brightness": 0.58,
        "timestamp": "2026-01-14T03:23:46.570603"
    },
    {
        "temperature": 19.76,
        "humidity": 54.12,
        "brightness": 0.84,
        "timestamp": "2026-01-14T03:23:26.514586"
    },
    {
        "temperature": 20.3,
        "humidity": 53.67,
        "brightness": 0.79,
        "timestamp": "2026-01-14T03:23:06.457036"
    },
    {
        "temperature": 20.18,
        "humidity": 57.14,
        "brightness": 0.59,
        "timestamp": "2026-01-14T03:22:46.393163"
    },
    {
        "temperature": 20.9,
        "humidity": 64.7,
        "brightness": 0.54,
        "timestamp": "2026-01-14T03:22:26.336014"
    },
    {
        "temperature": 21.5,
        "humidity": 60.01,
        "brightness": 0.51,
        "timestamp": "2026-01-14T03:22:06.220954"
    },
    {
        "temperature": 21.45,
        "humidity": 62.95,
        "brightness": 0.47,
        "timestamp": "2026-01-14T03:21:46.161552"
    },
    {
        "temperature": 19.66,
        "humidity": 64.52,
        "brightness": 0.58,
        "timestamp": "2026-01-14T03:21:26.117705"
    },
    {
        "temperature": 18.12,
        "humidity": 69.16,
        "brightness": 0.69,
        "timestamp": "2026-01-14T03:21:24.008574"
    },
    {
        "temperature": 21.07,
        "humidity": 53.55,
        "brightness": 0.76,
        "timestamp": "2026-01-14T03:21:03.953702"
    },
    {
        "temperature": 19.29,
        "humidity": 57.64,
        "brightness": 0.61,
        "timestamp": "2026-01-14T03:20:43.906448"
    }
]